HyoJuneTest/__init__.py
HyoJuneTest/example.py
HyoJuneTest-0.0.1.dist-info/METADATA
HyoJuneTest-0.0.1.dist-info/WHEEL
HyoJuneTest-0.0.1.dist-info/top_level.txt
HyoJuneTest-0.0.1.dist-info/RECORD
